jupyterlab_trash_mgmt_extension/__init__.py
jupyterlab_trash_mgmt_extension/_version.py
jupyterlab_trash_mgmt_extension/routes.py
jupyterlab_trash_mgmt_extension/tests/__init__.py
jupyterlab_trash_mgmt_extension/tests/conftest.py
jupyterlab_trash_mgmt_extension/tests/test_routes.py
jupyterlab_trash_mgmt_extension-1.0.12.data/data/etc/jupyter/jupyter_server_config.d/jupyterlab_trash_mgmt_extension.json
jupyterlab_trash_mgmt_extension-1.0.12.data/data/share/jupyter/labextensions/jupyterlab_trash_mgmt_extension/package.json
jupyterlab_trash_mgmt_extension-1.0.12.data/data/share/jupyter/labextensions/jupyterlab_trash_mgmt_extension/static/728.af55ecc67d680e5ba2ad.js
jupyterlab_trash_mgmt_extension-1.0.12.data/data/share/jupyter/labextensions/jupyterlab_trash_mgmt_extension/static/845.1f117d84b54e85a197d0.js
jupyterlab_trash_mgmt_extension-1.0.12.data/data/share/jupyter/labextensions/jupyterlab_trash_mgmt_extension/static/remoteEntry.2a4283a41c5b5cd1d22b.js
jupyterlab_trash_mgmt_extension-1.0.12.data/data/share/jupyter/labextensions/jupyterlab_trash_mgmt_extension/static/style.js
jupyterlab_trash_mgmt_extension-1.0.12.data/data/share/jupyter/labextensions/jupyterlab_trash_mgmt_extension/static/third-party-licenses.json
jupyterlab_trash_mgmt_extension-1.0.12.data/data/share/jupyter/labextensions/jupyterlab_trash_mgmt_extension/install.json
jupyterlab_trash_mgmt_extension-1.0.12.dist-info/METADATA
jupyterlab_trash_mgmt_extension-1.0.12.dist-info/WHEEL
jupyterlab_trash_mgmt_extension-1.0.12.dist-info/licenses/LICENSE
jupyterlab_trash_mgmt_extension-1.0.12.dist-info/RECORD
