Metadata-Version: 2.4
Name: jupyterlab_trash_mgmt_extension
Version: 1.0.12
Summary: Jupyterlab extension to introduce new left panel (along with browser, kernels, git, extensions) to allow management of trash - that is, empty bin, remove item from trash, restore item and show how much space items in the trash take
Project-URL: Homepage, https://github.com/stellarshenson/jupyterlab_trash_mgmt_extension
Project-URL: Bug Tracker, https://github.com/stellarshenson/jupyterlab_trash_mgmt_extension/issues
Project-URL: Repository, https://github.com/stellarshenson/jupyterlab_trash_mgmt_extension.git
Author-email: Stellars Henson <konrad.jelen@gmail.com>
License: BSD 3-Clause License
License-File: LICENSE
Keywords: jupyter,jupyterlab,jupyterlab-extension
Classifier: Framework :: Jupyter
Classifier: Framework :: Jupyter :: JupyterLab
Classifier: Framework :: Jupyter :: JupyterLab :: 4
Classifier: Framework :: Jupyter :: JupyterLab :: Extensions
Classifier: Framework :: Jupyter :: JupyterLab :: Extensions :: Prebuilt
Classifier: License :: OSI Approved :: BSD License
Classifier: Programming Language :: Python
Classifier: Programming Language :: Python :: 3
Classifier: Programming Language :: Python :: 3.10
Classifier: Programming Language :: Python :: 3.11
Classifier: Programming Language :: Python :: 3.12
Classifier: Programming Language :: Python :: 3.13
Classifier: Programming Language :: Python :: 3.14
Requires-Python: >=3.10
Requires-Dist: jupyter-server<3,>=2.4.0
Provides-Extra: dev
Requires-Dist: jupyterlab>=4; extra == 'dev'
Provides-Extra: test
Requires-Dist: coverage; extra == 'test'
Requires-Dist: pytest; extra == 'test'
Requires-Dist: pytest-asyncio; extra == 'test'
Requires-Dist: pytest-cov; extra == 'test'
Requires-Dist: pytest-jupyter[server]>=0.6.0; extra == 'test'
